{
  "schema_version": "1.0",
  "module": "hls",
  "status": "curated",
  "last_verified": "2026-06-05",
  "events": [
    {
      "name": "ready",
      "when": "Manifest HLS parseado, buffer inicial disponible para reproducción",
      "payload_shape": {},
      "must_precede": ["playing"]
    },
    {
      "name": "levelchange",
      "when": "ABR o cambio manual de nivel — ANTES de que el nuevo nivel esté en el buffer",
      "payload_shape": { "level": "number" },
      "optional": true
    },
    {
      "name": "levelchanged",
      "when": "El nuevo nivel está en el buffer y reproduciéndose",
      "payload_shape": { "level": "number" },
      "must_follow": ["levelchange"],
      "optional": true
    },
    {
      "name": "error",
      "when": "Error fatal de HLS (manifest inválido, segmentos no disponibles después de retries)",
      "payload_shape": { "fatal": "true", "type": "string", "details": "string" },
      "optional": true
    }
  ],
  "api_contracts": [
    {
      "method": "player.level (getter)",
      "signature": "get level(): number",
      "expected_behavior": "Retorna el nivel de calidad actual. -1 significa ABR automático.",
      "side_effects": []
    },
    {
      "method": "player.level (setter)",
      "signature": "set level(n: number): void",
      "expected_behavior": "Si n === -1: habilita ABR (modo automático). Si n >= 0: fija el nivel de calidad. El nivel se aplica cuando el siguiente segmento se descarga.",
      "side_effects": ["emite levelchange", "ABR deshabilitado si n !== -1"],
      "error_behavior": "Si n es mayor que el número de niveles disponibles → no-op o fallback al nivel máximo."
    },
    {
      "method": "player.levels (getter)",
      "signature": "get levels(): Array<{ height, bitrate, name }>",
      "expected_behavior": "Retorna la lista de niveles disponibles del manifest HLS. Solo disponible después de 'ready'.",
      "side_effects": []
    }
  ],
  "acceptance_criteria": [
    {
      "id": "AC-HLS-001",
      "scenario": "Stream HLS VOD ready en menos de 10s",
      "given": "Player con stream HLS VOD válido, sin ads",
      "when": "El player inicializa",
      "then": "El evento 'ready' se emite en menos de 10s. currentTime === 0. player.levels tiene al menos 1 nivel.",
      "priority": "MUST",
      "covered_by": ["tests/e2e/vod-playback.spec.ts", "tests/integration/"]
    },
    {
      "id": "AC-HLS-002",
      "scenario": "ABR — red degradada → nivel baja automáticamente",
      "given": "Player reproduciendo HLS con ABR habilitado (player.level === -1), velocidad de red reducida",
      "when": "El ancho de banda disponible cae por debajo del bitrate del nivel actual",
      "then": "player.level cambia a un nivel inferior. Se emiten levelchange y levelchanged en ese orden.",
      "priority": "SHOULD",
      "covered_by": ["tests/performance/"]
    },
    {
      "id": "AC-HLS-003",
      "scenario": "player.level = -1 habilita ABR",
      "given": "Player con nivel fijo (player.level === 2)",
      "when": "Se asigna player.level = -1",
      "then": "ABR se habilita. El nivel puede cambiar automáticamente basado en el ancho de banda.",
      "priority": "MUST",
      "covered_by": ["tests/e2e/"]
    },
    {
      "id": "AC-HLS-004",
      "scenario": "player.level = N fija nivel sin override de ABR",
      "given": "Player con ABR habilitado",
      "when": "Se asigna player.level = 2",
      "then": "El nivel se fija en 2. ABR no puede cambiarlo automáticamente. levelchange se emite.",
      "priority": "MUST",
      "covered_by": ["tests/e2e/"]
    },
    {
      "id": "AC-HLS-005",
      "scenario": "Segmento 404 → retry 3 veces, luego error fatal",
      "given": "Player reproduciendo HLS VOD, un segmento devuelve 404",
      "when": "hls.js intenta cargar el segmento",
      "then": "hls.js reintenta 3 veces. Si todos fallan, emite 'error' con fatal:true. El player no queda en loop infinito.",
      "priority": "MUST",
      "covered_by": ["tests/integration/hls-edge.spec.ts"]
    },
    {
      "id": "AC-HLS-006",
      "scenario": "DVR seekable window crece con el tiempo",
      "given": "Player reproduciendo stream HLS Live con DVR habilitado",
      "when": "Han pasado 30 segundos desde el inicio",
      "then": "player.seekable.end es mayor que el valor inicial. La ventana DVR está disponible para seek.",
      "priority": "MUST",
      "covered_by": ["tests/integration/"]
    },
    {
      "id": "AC-HLS-007",
      "scenario": "EXT-X-DISCONTINUITY no causa crash",
      "given": "Player reproduciendo stream HLS con segmento EXT-X-DISCONTINUITY en el manifest",
      "when": "El player alcanza el punto de discontinuidad",
      "then": "El player no crashea. La reproducción continúa. Puede haber un pequeño glitch visual pero no error fatal.",
      "priority": "MUST",
      "covered_by": ["tests/integration/hls-edge.spec.ts"]
    }
  ],
  "known_bugs": [],
  "do_not_reflag": [],
  "test_anti_patterns": [
    "No usar streams HLS públicos de producción en CI — son inestables",
    "No testear ABR sin simular condiciones de red — el ABR con red buena nunca cambia de nivel",
    "player.levels solo disponible después de 'ready' — no leer antes"
  ]
}
